asdk_plugin_analytics/__init__.py
asdk_plugin_analytics/api_registry.py
asdk_plugin_analytics/domain_apis_list.json
asdk_plugin_analytics/agraph/__init__.py
asdk_plugin_analytics/agraph/analytics/__init__.py
asdk_plugin_analytics/agraph/analytics/data/__init__.py
asdk_plugin_analytics/agraph/analytics/data/climate/__init__.py
asdk_plugin_analytics/agraph/analytics/data/climate/v1/__init__.py
asdk_plugin_analytics/agraph/analytics/data/climate/v1/ClimateAPI/__init__.py
asdk_plugin_analytics/agraph/analytics/data/climate/v1/ClimateAPI/api_client.py
asdk_plugin_analytics/agraph/analytics/data/climate/v1/ClimateAPI/api_response.py
asdk_plugin_analytics/agraph/analytics/data/climate/v1/ClimateAPI/configuration.py
asdk_plugin_analytics/agraph/analytics/data/climate/v1/ClimateAPI/exceptions.py
asdk_plugin_analytics/agraph/analytics/data/climate/v1/ClimateAPI/rest.py
asdk_plugin_analytics/agraph/analytics/data/climate/v1/ClimateAPI/swagger.json
asdk_plugin_analytics/agraph/analytics/data/climate/v1/ClimateAPI/api/__init__.py
asdk_plugin_analytics/agraph/analytics/data/climate/v1/ClimateAPI/api/default_climate_api.py
asdk_plugin_analytics/agraph/analytics/data/climate/v1/ClimateAPI/models/__init__.py
asdk_plugin_analytics/agraph/analytics/data/climate/v1/ClimateAPI/models/any.py
asdk_plugin_analytics/agraph/analytics/data/climate/v1/ClimateAPI/models/climate_api_retrieve_climate_data_as_of_date400_response.py
asdk_plugin_analytics/agraph/analytics/data/climate/v1/ClimateAPI/models/climatev1_segment.py
asdk_plugin_analytics/agraph/analytics/data/climate/v1/ClimateAPI/models/rpc_status.py
asdk_plugin_analytics/agraph/analytics/data/climate/v1/ClimateAPI/models/types_analytic_data_value.py
asdk_plugin_analytics/agraph/analytics/data/climate/v1/ClimateAPI/models/v1_climate_common_data_set.py
asdk_plugin_analytics/agraph/analytics/data/climate/v1/ClimateAPI/models/v1_climate_common_metrics.py
asdk_plugin_analytics-2.0.0b2.dist-info/METADATA
asdk_plugin_analytics-2.0.0b2.dist-info/WHEEL
asdk_plugin_analytics-2.0.0b2.dist-info/top_level.txt
asdk_plugin_analytics-2.0.0b2.dist-info/RECORD
